overview_client/__init__.py
overview_client/api/__init__.py
overview_client/api/capture_api.py
overview_client/api/recipe_api.py
overview_client/api_client.py
overview_client/api_response.py
overview_client/configuration.py
overview_client/exceptions.py
overview_client/models/__init__.py
overview_client/models/capture.py
overview_client/models/capture_classification_result_inner.py
overview_client/models/capture_classification_result_inner_block_classification_classes.py
overview_client/models/capture_classification_result_inner_block_classification_classes_block_roi_inspection_type_params.py
overview_client/models/capture_classification_result_inner_roi_result.py
overview_client/models/capture_classification_result_inner_roi_result_block_roi_region_params.py
overview_client/models/recipe_id.py
overview_client/py.typed
overview_client/rest.py
overview_client-0.0.1.dist-info/METADATA
overview_client-0.0.1.dist-info/WHEEL
overview_client-0.0.1.dist-info/RECORD
