Metadata-Version: 2.1
Name: overview_client
Version: 0.0.1
Summary: Overview Smart AI Cameras API
Home-page: https://github.com/GIT_USER_ID/GIT_REPO_ID
License: MIT
Keywords: OpenAPI,OpenAPI-Generator,Overview Smart AI Cameras API
Author: OpenAPI Generator Community
Author-email: lucas.vandroux@viun.tech
Requires-Python: >=3.8,<4.0
Classifier: License :: OSI Approved :: MIT License
Classifier: Programming Language :: Python :: 3
Classifier: Programming Language :: Python :: 3.8
Classifier: Programming Language :: Python :: 3.9
Classifier: Programming Language :: Python :: 3.10
Classifier: Programming Language :: Python :: 3.11
Classifier: Programming Language :: Python :: 3.12
Classifier: Programming Language :: Python :: 3.13
Requires-Dist: pydantic (>=2)
Requires-Dist: python-dateutil (>=2.8.2)
Requires-Dist: typing-extensions (>=4.7.1)
Requires-Dist: urllib3 (>=1.25.3,<3.0.0)
Project-URL: Repository, https://github.com/GIT_USER_ID/GIT_REPO_ID
